pron/__init__.py
pron/pron.py
pron-0.1.2.dist-info/LICENSE
pron-0.1.2.dist-info/METADATA
pron-0.1.2.dist-info/WHEEL
pron-0.1.2.dist-info/top_level.txt
pron-0.1.2.dist-info/RECORD
