Metadata-Version: 2.1
Name: pron
Version: 0.1.2
Summary: Read and write Python Recognizable Object Notation
Author-email: pron <fredrik@atmer.se>
License: GNU GENERAL PUBLIC LICENSE
Project-URL: Homepage, https://github.com/BathroomEpiphanies/python3-pron
Keywords: pron
Classifier: License :: OSI Approved :: GNU General Public License v3 (GPLv3)
Classifier: Programming Language :: Python :: 3
Requires-Python: >=3.6
License-File: LICENSE
Provides-Extra: dev
Requires-Dist: pip-tools ; extra == 'dev'
Requires-Dist: pytest ; extra == 'dev'
